MANIFEST.in
README.md
requirements.txt
setup.py
RangeMinQuery/SegmentTree.py
RangeMinQuery/__init__.py
RangeMinQuery.egg-info/PKG-INFO
RangeMinQuery.egg-info/SOURCES.txt
RangeMinQuery.egg-info/dependency_links.txt
RangeMinQuery.egg-info/requires.txt
RangeMinQuery.egg-info/top_level.txt