Metadata-Version: 2.1
Name: RangeMinQuery
Version: 0.2
Summary: Solving the Range Minimum Query problem
Home-page: https://github.com/chuanconggao/RangeMinQuery
Author: Chuancong Gao
Author-email: chuancong@gmail.com
License: MIT
Download-URL: https://github.com/chuanconggao/RangeMinQuery/tarball/0.2
Keywords: range-minimum-query
Platform: UNKNOWN
Classifier: Operating System :: OS Independent
Classifier: Programming Language :: Python
Classifier: Programming Language :: Python :: 2
Classifier: Programming Language :: Python :: 3
